odoo/addons/pos_bypass_global_discount/README.rst
odoo/addons/pos_bypass_global_discount/__init__.py
odoo/addons/pos_bypass_global_discount/__manifest__.py
odoo/addons/pos_bypass_global_discount/i18n/it.po
odoo/addons/pos_bypass_global_discount/i18n/pos_bypass_global_discount.pot
odoo/addons/pos_bypass_global_discount/models/__init__.py
odoo/addons/pos_bypass_global_discount/models/pos_session.py
odoo/addons/pos_bypass_global_discount/readme/CONTRIBUTORS.rst
odoo/addons/pos_bypass_global_discount/readme/DESCRIPTION.rst
odoo/addons/pos_bypass_global_discount/static/description/icon.png
odoo/addons/pos_bypass_global_discount/static/description/index.html
odoo/addons/pos_bypass_global_discount/static/src/js/models.js
odoo/addons/pos_bypass_global_discount/static/src/tours/PosBypassGlobalDiscount.esm.js
odoo/addons/pos_bypass_global_discount/tests/__init__.py
odoo/addons/pos_bypass_global_discount/tests/test_bypass_global_discount.py
odoo_addon_pos_bypass_global_discount-16.0.1.0.1.dist-info/METADATA
odoo_addon_pos_bypass_global_discount-16.0.1.0.1.dist-info/WHEEL
odoo_addon_pos_bypass_global_discount-16.0.1.0.1.dist-info/top_level.txt
odoo_addon_pos_bypass_global_discount-16.0.1.0.1.dist-info/RECORD
